[{
        "index": 1,
        "name": "glassdoor-reviews",
        "link": "https://rmd-jhx-app.herokuapp.com",
        "time": "2019",
        "image": "images/glassdoor-reviews.png"
    }, {
        "index": 2,
        "name": "congressional-bills",
        "link": "https://congressional-bill-app.herokuapp.com/",
        "time": "2019",
        "image": "images/congressional-bills.png"
    },{
        "index": 3,
        "name": "climate-change",
        "link": "https://impact2018.abtassociates.com/climate_change",
        "time": "2018",
        "image": "images/abt-climatechange.png"
    },{
        "index": 4,
        "name": "hud-stella",
        "link": "https://files.hudexchange.info/resources/documents/Stella-System-Performance-Map-Guide.pdf",
        "time": "2018",
        "image": "images/hud-stella.png"
    },
    {
        "index": 5,
        "name": "google-hilary-clinton",
        "link": "http://www.googletransparencyproject.org/articles/lessons-googles-support-hillary-clinton",
        "time": "2016",
        "image": "images/hillary-google.png"
    },
    {
        "index": 6,
        "name": "health-concerns",
        "link": "https://katielong.github.io/health_concerns/",
        "time": "2016",
        "image": "images/health-concern.png"
    },
    {
        "index": 7,
        "name": "land-housing-prices",
        "link": "https://www.yueklong.com/Land_Housing_Price/zoomin.html",
        "time": "2016",
        "image": "images/changsha-map.png"
    }
]